README.md
setup.py
client/__init__.py
client/__main__.py
client/methods.py
gensim/__init__.py
gensim/downloader.py
gensim/interfaces.py
gensim/matutils.py
gensim/nosy.py
gensim/utils.py
gensim/corpora/__init__.py
gensim/corpora/bleicorpus.py
gensim/corpora/csvcorpus.py
gensim/corpora/dictionary.py
gensim/corpora/hashdictionary.py
gensim/corpora/indexedcorpus.py
gensim/corpora/lowcorpus.py
gensim/corpora/malletcorpus.py
gensim/corpora/mmcorpus.py
gensim/corpora/opinosiscorpus.py
gensim/corpora/sharded_corpus.py
gensim/corpora/svmlightcorpus.py
gensim/corpora/textcorpus.py
gensim/corpora/ucicorpus.py
gensim/corpora/wikicorpus.py
gensim/models/__init__.py
gensim/models/_fasttext_bin.py
gensim/models/atmodel.py
gensim/models/basemodel.py
gensim/models/bm25model.py
gensim/models/callbacks.py
gensim/models/coherencemodel.py
gensim/models/doc2vec.py
gensim/models/ensemblelda.py
gensim/models/fasttext.py
gensim/models/hdpmodel.py
gensim/models/keyedvectors.py
gensim/models/lda_dispatcher.py
gensim/models/lda_worker.py
gensim/models/ldamodel.py
gensim/models/ldamulticore.py
gensim/models/ldaseqmodel.py
gensim/models/logentropy_model.py
gensim/models/lsi_dispatcher.py
gensim/models/lsi_worker.py
gensim/models/lsimodel.py
gensim/models/nmf.py
gensim/models/normmodel.py
gensim/models/phrases.py
gensim/models/poincare.py
gensim/models/rpmodel.py
gensim/models/tfidfmodel.py
gensim/models/translation_matrix.py
gensim/models/word2vec.py
gensim/parsing/__init__.py
gensim/parsing/porter.py
gensim/parsing/preprocessing.py
gensim/scripts/__init__.py
gensim/scripts/benchmark.py
gensim/scripts/glove2word2vec.py
gensim/scripts/make_wiki.py
gensim/scripts/make_wiki_online.py
gensim/scripts/make_wiki_online_nodebug.py
gensim/scripts/make_wikicorpus.py
gensim/scripts/package_info.py
gensim/scripts/segment_wiki.py
gensim/scripts/word2vec2tensor.py
gensim/scripts/word2vec_standalone.py
gensim/similarities/__init__.py
gensim/similarities/annoy.py
gensim/similarities/docsim.py
vertex_voyage.egg-info/PKG-INFO
vertex_voyage.egg-info/SOURCES.txt
vertex_voyage.egg-info/dependency_links.txt
vertex_voyage.egg-info/entry_points.txt
vertex_voyage.egg-info/requires.txt
vertex_voyage.egg-info/top_level.txt
